README.md
setup.cfg
setup.py
shortlink/__init__.py
shortlink/shortlink.py
shortlink.egg-info/PKG-INFO
shortlink.egg-info/SOURCES.txt
shortlink.egg-info/dependency_links.txt
shortlink.egg-info/requires.txt
shortlink.egg-info/top_level.txt